poetry_versions_plugin/__init__.py
poetry_versions_plugin/plugin.py
poetry_versions_plugin/services.py
poetry_versions_plugin/utils.py
poetry_versions_plugin/versions.py
poetry_versions_plugin-1.1.1.dist-info/METADATA
poetry_versions_plugin-1.1.1.dist-info/WHEEL
poetry_versions_plugin-1.1.1.dist-info/entry_points.txt
poetry_versions_plugin-1.1.1.dist-info/RECORD
