Metadata-Version: 2.3
Name: poetry-versions-plugin
Version: 1.1.1
Summary: Poetry plugin that automates version management and records Git information for Python projects.
License: Apache-2.0
Keywords: packaging,poetry,plugin,versioning,git
Author: xy.kong
Author-email: xy.kong@gmail.com
Requires-Python: >=3.9,<4
Classifier: License :: OSI Approved :: Apache Software License
Classifier: Programming Language :: Python :: 3
Classifier: Programming Language :: Python :: 3.9
Classifier: Programming Language :: Python :: 3.10
Classifier: Programming Language :: Python :: 3.11
Classifier: Programming Language :: Python :: 3.12
Classifier: Programming Language :: Python :: 3.13
Requires-Dist: gitpython (>=3.1.43,<4.0.0)
Requires-Dist: pexpect (>=4.9.0,<5.0.0)
Requires-Dist: poetry (>=1.2.0)
Project-URL: Documentation, https://github.com/xykong/poetry-versions-plugin/blob/master/README.md
Project-URL: Homepage, https://github.com/xykong/poetry-versions-plugin
Project-URL: Repository, https://github.com/xykong/poetry-versions-plugin
